seeq/addons/mps/__init__.py
seeq/addons/mps/__main__.py
seeq/addons/mps/_copy.py
seeq/addons/mps/_mps.py
seeq/addons/mps/_mps_sdl_ui.py
seeq/addons/mps/_version.py
seeq/addons/mps/deployment_notebook/multivariate_pattern_search_ui.ipynb
seeq/addons/mps/utils/__init__.py
seeq/addons/mps/utils/_common.py
seeq/addons/mps/utils/_permissions.py
seeq/addons/mps/utils/_sdl.py
seeq_mps-0.3.9.dist-info/LICENSE
seeq_mps-0.3.9.dist-info/METADATA
seeq_mps-0.3.9.dist-info/NOTICE
seeq_mps-0.3.9.dist-info/WHEEL
seeq_mps-0.3.9.dist-info/top_level.txt
seeq_mps-0.3.9.dist-info/RECORD
