Metadata-Version: 2.1
Name: seeq-mps
Version: 0.3.9
Summary: Finds and measures similar events defined across multiple variables
Home-page: https://github.com/seeq12/seeq-mps
Author: Seeq Corporation
Author-email: applied.research@seeq.com
License: Apache License 2.0
Platform: Linux
Platform: Windows
Classifier: Programming Language :: Python :: 3.7
Classifier: License :: OSI Approved :: Apache Software License
Classifier: Operating System :: OS Independent
Requires-Python: >=3.7
License-File: LICENSE
License-File: NOTICE
Requires-Dist: dtaidistance (>=1.2.3)
Requires-Dist: IPython (>=7.21.0)
Requires-Dist: ipywidgets (>=7.6.3)
Requires-Dist: mass-ts (>=0.1.4)
Requires-Dist: numpy (>=1.22.2)
Requires-Dist: pandas (>=1.4.1)
Requires-Dist: pandas (<2.0.0)
Requires-Dist: scipy (>=1.5.4)
